Workbook

Sheet Parameters
A1: Параметр | B1: Значение | C1: Единица | D1: Примечание
A2: Planning_Horizon | B2: 5 | C2: лет | D2: Горизонт планирования
A3: Discount_Rate | B3: 0.12 | C3: % | D3: Ставка дисконтирования (hurdle rate)
A4: Inflation_Rate | B4: 0.075 | C4: % | D4: Ожидаемая инфляция
A5: Growth_Rate_Users | B5: 0.05 | C5: % | D5: Ежегодный рост пользователей
A6: Tax_Rate | B6: 0.2 | C6: % | D6: Налог на прибыль
A7: FTE_Fully_Loaded_Cost | B7: 1200000 | C7: руб/год | D7: Полная стоимость 1 FTE
A8: Physician_Hourly_Rate | B8: 3500 | C8: руб/час | D8: Стоимость часа врача
A9: Nurse_Hourly_Rate | B9: 1800 | C9: руб/час | D9: Стоимость часа медсестры
A10: Cost_per_Medical_Error | B10: 50000 | C10: руб/ошибка | D10: Средняя стоимость ошибки
A11: Cost_per_Day_LOS | B11: 15000 | C11: руб/койко-день | D11: Стоимость дня госпитализации
A12: Physician_Turnover_Cost | B12: 750000 | C12: руб/врача | D12: Стоимость замены врача
A13: Confidence_Factor_Soft | B13: 0.85 | C13: % | D13: Коэффициент доверия к soft benefits
A14: Working_Days_Per_Year | B14: 220 | C14: дней | D14: Рабочих дней в году

Sheet Costs_TCO
A1: Категория | B1: Статья | C1: Сумма_Год0 | D1: Формула_Примечание | F1: Acquisition Costs
A2: Software | B2: Лицензии_первоначальные | C2: 500000 | D2: Разовая покупка
A3: Software | B3: Кастомизация | C3: 300000 | D3: Доработка под процессы
A4: Hardware | B4: Серверы_оборудование | C4: 0 | D4: 0 для cloud-решений
A5: Hardware | B5: Сетевое_оборудование | C5: 0 | D5: При необходимости
A6: Implementation | B6: Интеграция_МИС_ЕГИСЗ | C6: 400000 | D6: Критично для мед. систем
A7: Implementation | B7: Миграция_данных | C7: 150000 | D7: Перенос исторических данных
A8: Implementation | B8: Тестирование_ИБ | C8: 200000 | D8: Пентест + аудит 152-ФЗ
A9: Training | B9: Обучение_персонала | C9: 100000 | D9: Врачи + медсёстры + админы
A10: Training | B10: Документация | C10: 50000 | D10: Инструкции + регламенты
A11: Project_Mgmt | B11: Внутренний_PM | C11: 150000 | D11: Выделение времени PM
A12: Project_Mgmt | B12: Внешний_консультант | C12: 0 | D12: При необходимости
A13: Compliance | B13: Аудит_соответствия | C13: 100000 | D13: 152-ФЗ / HIPAA
A14: Compliance | B14: Сертификация | C14: 0 | D14: При необходимости
A15: ИТОГО_Acquisition | C15: =SUM(C2:C14) -> 1950000 | D15: Автосумма
A17: Категория | B17: Статья | C17: Год1 | D17: Формула_роста_на_след_год | F17: Operational Costs
A18: Software | B18: Подписка_лицензии | C18: 300000 | D18: =C18*(1+Parameters!$B$3) -> 336000
A19: Software | B19: Обновления_патчи | C19: 50000 | D19: =Включено_в_подписку -> #NAME?
A20: Infrastructure | B20: Хостинг_Cloud | C20: 120000 | D20: =B4*(1+Parameters!$B$4) -> #VALUE!
A21: Infrastructure | B21: Резервное_копирование | C21: 30000 | D21: =Обязательно_для_мед_данных -> #NAME?
A22: Support | B22: Техподдержка_вендор | C22: 80000 | D22: =%_от_лицензии
A23: Support | B23: Внутренняя_поддержка | C23: 200000 | D23: =Время_ИТ_специалистов -> #NAME?
A24: Security | B24: Мониторинг_ИБ | C24: 60000 | D24: =SIEM_аудит_логов -> #NAME?
A25: Security | B25: Пентест_ежегодный | C25: 100000 | D25: =Требование_регуляторов -> #NAME?
A26: Compliance | B26: Аудит_152-ФЗ | C26: 80000 | D26: =Ежегодный_аудит -> #NAME?
A27: Compliance | B27: Отчётность_ЕГИСЗ | C27: 40000 | D27: =Росздравнадзор -> #NAME?
A28: Training | B28: Обучение_новых | C28: 50000 | D28: =B11*(1+Parameters!$B$4) -> #VALUE!
A29: Training | B29: Рефреш_тренинги | C29: 30000 | D29: =Поддержание_компетенций -> #NAME?
A30: ИТОГО_Operational_Год1 | C30: =SUM(C2:C13) -> 1950000 | D30: Автосумма
A32: Роль | B32: FTE_доля | C32: Годовая_стоимость | D32: Формула_расчёта | F32: Resource Costs
A33: Product_Owner | B33: 0.2 | C33: =B2*Parameters!$B$6 -> #VALUE! | D33: =FTE*FTE_Cost -> #NAME?
A34: Scrum_Master | B34: 0.1 | C34: =B3*Parameters!$B$6 -> #VALUE! | D34: =FTE*FTE_Cost -> #NAME?
A35: Developer | B35: 0.5 | C35: =B4*Parameters!$B$6 -> #VALUE! | D35: =FTE*FTE_Cost -> #NAME?
A36: QA_Engineer | B36: 0.2 | C36: =B5*Parameters!$B$6 -> #VALUE! | D36: =FTE*FTE_Cost -> #NAME?
A37: Clinical_Champion | B37: 0.1 | C37: =B6*Parameters!$B$6 -> #VALUE! | D37: =Врач-эксперт -> #NAME?
A38: ИТОГО_Resource | C38: =SUM(C2:C6) -> 1200000 | D38: Автосумма
